LICENSE.txt
README.md
pyproject.toml
setup.cfg
setup.py
data/data_file
src/pydatatools.egg-info/PKG-INFO
src/pydatatools.egg-info/SOURCES.txt
src/pydatatools.egg-info/dependency_links.txt
src/pydatatools.egg-info/entry_points.txt
src/pydatatools.egg-info/requires.txt
src/pydatatools.egg-info/top_level.txt
src/sample/__init__.py
src/sample/simple.py