Metadata-Version: 2.1
Name: pydatatools
Version: 1.0.2
Summary: A pydatatools Python project
Home-page: https://github.com/pypa/pydatatools
Author: A. Random Developer
Author-email: skyli114@126.com
License: UNKNOWN
Project-URL: Bug Reports, https://github.com/melicent114/pydata/issues
Project-URL: Say Thanks!, https://github.com/melicent114/pydata
Project-URL: Source, https://github.com/melicent114/pydata
Keywords: pydatatools,setuptools,development
Platform: UNKNOWN
Classifier: Development Status :: 3 - Alpha
Classifier: Intended Audience :: Developers
Classifier: Topic :: Software Development :: Build Tools
Classifier: License :: OSI Approved :: MIT License
Classifier: Programming Language :: Python :: 3
Classifier: Programming Language :: Python :: 3.6
Classifier: Programming Language :: Python :: 3.7
Classifier: Programming Language :: Python :: 3.8
Classifier: Programming Language :: Python :: 3.9
Classifier: Programming Language :: Python :: 3.10
Classifier: Programming Language :: Python :: 3 :: Only
Requires-Python: >=3.6, <4
Provides-Extra: dev
Provides-Extra: test
